exponent/__init__.py
exponent/cli.py
exponent/py.typed
exponent/commands/checkout_commands.py
exponent/commands/cloud_commands.py
exponent/commands/common.py
exponent/commands/config_commands.py
exponent/commands/run_commands.py
exponent/commands/settings.py
exponent/commands/types.py
exponent/commands/upgrade.py
exponent/commands/utils.py
exponent/core/config.py
exponent/core/container_build/__init__.py
exponent/core/container_build/types.py
exponent/core/graphql/__init__.py
exponent/core/graphql/base_client.py
exponent/core/graphql/client.py
exponent/core/graphql/get_chats_query.py
exponent/core/graphql/mutations.py
exponent/core/graphql/queries.py
exponent/core/graphql/subscriptions.py
exponent/core/graphql/generated_client/__init__.py
exponent/core/graphql/generated_client/base_client.py
exponent/core/graphql/generated_client/base_model.py
exponent/core/graphql/generated_client/chats.py
exponent/core/graphql/generated_client/client.py
exponent/core/graphql/generated_client/create_cloud_chat_from_repository.py
exponent/core/graphql/generated_client/enable_cloud_repository.py
exponent/core/graphql/generated_client/enums.py
exponent/core/graphql/generated_client/github_repositories.py
exponent/core/graphql/generated_client/halt_chat_stream.py
exponent/core/graphql/generated_client/input_types.py
exponent/core/graphql/generated_client/rebuild_cloud_repository.py
exponent/core/graphql/generated_client/refresh_api_key.py
exponent/core/graphql/generated_client/report_sandbox_info.py
exponent/core/graphql/generated_client/set_login_complete.py
exponent/core/graphql/generated_client/start_chat_turn.py
exponent/core/graphql/operations/chats.graphql
exponent/core/graphql/operations/create_cloud_chat_from_repository.graphql
exponent/core/graphql/operations/enable_cloud_repository.graphql
exponent/core/graphql/operations/github_repositories.graphql
exponent/core/graphql/operations/halt_chat_stream.graphql
exponent/core/graphql/operations/rebuild_cloud_repository.graphql
indent-0.1.42.dist-info/METADATA
indent-0.1.42.dist-info/WHEEL
indent-0.1.42.dist-info/entry_points.txt
indent-0.1.42.dist-info/RECORD
