Metadata-Version: 2.4
Name: indent
Version: 0.1.42
Summary: Indent is an AI Pair Programmer
Author-email: Sashank Thupukari <sashank@exponent.run>
Requires-Python: <3.13,>=3.10
Requires-Dist: aiohttp<3.14,>=3.13.2
Requires-Dist: anyio<4.13,>=4.6.0
Requires-Dist: async-timeout<5,>=4.0.3; python_version < '3.11'
Requires-Dist: beautifulsoup4[chardet]<4.15,>=4.13.4
Requires-Dist: certifi<2027,>=2024.8.30
Requires-Dist: click<9,>=8.1.7
Requires-Dist: colour<0.2,>=0.1.5
Requires-Dist: gitignore-parser<0.2,>=0.1.11
Requires-Dist: gql[httpx,websockets]~=4.0
Requires-Dist: httpx>=0.28.1
Requires-Dist: ipykernel<7,>=6.29.4
Requires-Dist: jupyter-client<8.9,>=8.6.1
Requires-Dist: msgspec<0.21,>=0.19.0
Requires-Dist: packaging~=24.1
Requires-Dist: pip<26,>=25.0.1
Requires-Dist: psutil<7,>=5.9.0
Requires-Dist: pydantic-ai<2,>=0.0.30
Requires-Dist: pydantic-settings<3,>=2.2.1
Requires-Dist: pydantic[email]<3,>=2.6.4
Requires-Dist: pygit2<1.20,>=1.15.0
Requires-Dist: python-ripgrep>=0.0.9
Requires-Dist: pyyaml<6.1,>=6.0.2
Requires-Dist: questionary<2.2,>=2.0.1
Requires-Dist: rich<15,>=13.7.1
Requires-Dist: sentry-sdk<3,>=2.1.1
Requires-Dist: websockets~=15.0
